bank_base_gt/__init__.py
bank_base_gt/bank.py
bank_base_gt-0.5.1.dist-info/LICENSE
bank_base_gt-0.5.1.dist-info/METADATA
bank_base_gt-0.5.1.dist-info/WHEEL
bank_base_gt-0.5.1.dist-info/top_level.txt
bank_base_gt-0.5.1.dist-info/RECORD
