Metadata-Version: 2.1
Name: bank-base-gt
Version: 0.5.1
Summary: Bank Parser Base Package for banks in Guatemala. Provides models and base structure
Home-page: https://github.com/gt-banks-parser/banks-parser-base
Author: Carlos Simon
Author-email: dev@csimon.dev
Classifier: Programming Language :: Python :: 3.6
Classifier: Development Status :: 4 - Beta
Classifier: License :: OSI Approved :: MIT License
Classifier: Operating System :: OS Independent
Classifier: Intended Audience :: Financial and Insurance Industry
Classifier: Intended Audience :: Information Technology
Classifier: Topic :: Office/Business :: Financial
Classifier: Topic :: Utilities
Requires-Python: >=3.6
License-File: LICENSE
Requires-Dist: requests
Requires-Dist: beautifulsoup4
Requires-Dist: money
Requires-Dist: babel
